src/__init__.py
src/aboutdialog.py
src/canvas.py
src/inittab.py
src/main.py
src/mainwindow.py
src/menubar.py
src/palette.py
src/palettebutton.py
src/utils.py
mespaint-0.0.4.dist-info/LICENSE
mespaint-0.0.4.dist-info/METADATA
mespaint-0.0.4.dist-info/WHEEL
mespaint-0.0.4.dist-info/entry_points.txt
mespaint-0.0.4.dist-info/top_level.txt
mespaint-0.0.4.dist-info/RECORD
