Metadata-Version: 2.1
Name: mespaint
Version: 0.0.4
Summary: custom palette changer for indexed PNGs
Home-page: https://github.com/menga-team/MESpaint
Author: 0.0.4
Author-email: menga.team@yandex.com
License: MIT
License-File: LICENSE
Requires-Dist: PyQt5
Requires-Dist: PyQt5-Qt5
Requires-Dist: PyQt5-sip
